dhcpkit_kafka/__init__.py
dhcpkit_kafka/message_registry.py
dhcpkit_kafka/messages.py
dhcpkit_kafka/server_extension/__init__.py
dhcpkit_kafka/server_extension/component.xml
dhcpkit_kafka/server_extension/config.py
dhcpkit_kafka/tests/__init__.py
dhcpkit_kafka/tests/messages/__init__.py
dhcpkit_kafka/tests/messages/test_dhcp_kafka_message.py
dhcpkit_kafka/tests/messages/test_kafka_message.py
dhcpkit_kafka/tests/messages/test_unknown_kafka_message.py
dhcpkit_kafka-1.0.0.dist-info/DESCRIPTION.rst
dhcpkit_kafka-1.0.0.dist-info/METADATA
dhcpkit_kafka-1.0.0.dist-info/RECORD
dhcpkit_kafka-1.0.0.dist-info/WHEEL
dhcpkit_kafka-1.0.0.dist-info/entry_points.txt
dhcpkit_kafka-1.0.0.dist-info/metadata.json
dhcpkit_kafka-1.0.0.dist-info/top_level.txt
