Metadata-Version: 2.0
Name: dhcpkit-kafka
Version: 1.0.0
Summary: Kafka extensions to DHCPKit
Home-page: https://github.com/sjm-steffann/dhcpkit_kafka
Author: Sander Steffann
Author-email: sander@steffann.nl
License: GPLv3
Keywords: dhcp server ipv6 kafka looking-glass
Platform: UNKNOWN
Classifier: Development Status :: 5 - Production/Stable
Classifier: Environment :: Console
Classifier: Environment :: No Input/Output (Daemon)
Classifier: Environment :: Web Environment
Classifier: Framework :: Django
Classifier: Intended Audience :: Developers
Classifier: Intended Audience :: Information Technology
Classifier: Intended Audience :: System Administrators
Classifier: License :: OSI Approved :: GNU General Public License v3 (GPLv3)
Classifier: Natural Language :: English
Classifier: Operating System :: MacOS :: MacOS X
Classifier: Operating System :: POSIX
Classifier: Operating System :: Unix
Classifier: Programming Language :: Python :: 3 :: Only
Classifier: Programming Language :: Python :: 3.4
Classifier: Programming Language :: Python :: 3.5
Classifier: Topic :: Internet
Classifier: Topic :: System :: Networking
Classifier: Topic :: System :: Systems Administration
Requires-Dist: dhcpkit (>=0.9.0)
Requires-Dist: pykafka
